flake8_colors/__init__.py
flake8_colors/formatter.py
flake8_colors-0.1.8.dist-info/LICENSE
flake8_colors-0.1.8.dist-info/METADATA
flake8_colors-0.1.8.dist-info/WHEEL
flake8_colors-0.1.8.dist-info/entry_points.txt
flake8_colors-0.1.8.dist-info/top_level.txt
flake8_colors-0.1.8.dist-info/RECORD
